portfolio/__init__.py
portfolio/portfolio_report.py
tests/__init__.py
tests/conftest.py
tests/test_io.py
portfolio_report_SMACDOUGALL_BOT-0.0.4.dist-info/LICENCE
portfolio_report_SMACDOUGALL_BOT-0.0.4.dist-info/METADATA
portfolio_report_SMACDOUGALL_BOT-0.0.4.dist-info/WHEEL
portfolio_report_SMACDOUGALL_BOT-0.0.4.dist-info/entry_points.txt
portfolio_report_SMACDOUGALL_BOT-0.0.4.dist-info/top_level.txt
portfolio_report_SMACDOUGALL_BOT-0.0.4.dist-info/RECORD
