Metadata-Version: 2.1
Name: portfolio-report-SMACDOUGALL-BOT
Version: 0.0.4
Summary: Generates a CSV of portfilio holdings and their performance
Home-page: UNKNOWN
Author: Steve MacDougall
Author-email: sgmacdougall@gmail.com
License: UNKNOWN
Platform: UNKNOWN
Classifier: Programming Language :: Python :: 3
Classifier: License :: OSI Approved :: MIT License
Classifier: Operating System :: OS Independent
Requires-Python: >=3.6
Requires-Dist: pytest (>=4.3.1pylint>=2.3.1six>=1.12requests>=2.22requests-mock>=1.7)
